djongo_orm/__init__.py
djongo_orm/fields.py
djongo_orm-1.0.4.dist-info/LICENSE.TXT
djongo_orm-1.0.4.dist-info/METADATA
djongo_orm-1.0.4.dist-info/WHEEL
djongo_orm-1.0.4.dist-info/top_level.txt
djongo_orm-1.0.4.dist-info/RECORD
