Metadata-Version: 2.1
Name: djongo_orm
Version: 1.0.4
Summary: Djongo ORM
Home-page: 
Author: Cherish
Author-email: 
License: MIT
Classifier: Development Status :: 4 - Beta
Classifier: Intended Audience :: Developers
Classifier: Programming Language :: Python :: 3
Classifier: Programming Language :: Python :: 3.6
Classifier: Programming Language :: Python :: 3.7
License-File: LICENSE.TXT
Requires-Dist: Django>=3.0.0
Requires-Dist: djongo>=1.3.0
